Workbook

Sheet Staff
A1: Staff | B1: Amount | C1: Gross Annual Salary | D1: Annual Salary Cost | E1: TOTAL
A2: Project Manager | B2: 1 | C2: 42000 | D2: =C2*1.3 -> 54600 | E2: =D2*B2 -> 54600
A3: Lead Researcher | B3: 1 | C3: 42000 | D3: =C3*1.3 -> 54600 | E3: =D3*B3 -> 54600
A4: Software Engineer | B4: 1 | C4: 32000 | D4: =C4*1.3 -> 41600 | E4: =D4*B4 -> 41600
A5: Junior Researcher | B5: 1 | C5: 25000 | D5: =C5*1.3 -> 32500 | E5: =D5*B5 -> 32500
A6: Junior Researcher II | B6: 1 | C6: 25000 | D6: =C6*1.3 -> 32500 | E6: =D6*B6 -> 32500
A7: TOTAL | B7: =SUM(B2:B6) -> 5 | E7: =SUM(E2:E6) -> 215800

Sheet Staff Productivity
B2: Staff | C2: TOTAL | D2: Prod (%) | E2: Direct Cost | F2: IC(%) | G2: Indirect Cost
B3: =Staff!A2 -> Project Manager | C3: =Staff!E2 -> 54600 | D3: 0 | E3: 0 | F3: =1-D3 -> 1 | G3: =C3*F3 -> 54600
B4: =Staff!A3 -> Lead Researcher | C4: =Staff!E3 -> 54600 | D4: 0.7 | E4: =C4*D4 -> 38220 | F4: =1-D4 -> 0.3 | G4: =C4*F4 -> 16380
B5: =Staff!A4 -> Software Engineer | C5: =Staff!E4 -> 41600 | D5: 0.8 | E5: =C5*D5 -> 33280 | F5: =1-D5 -> 0.2 | G5: =C5*F5 -> 8320
B6: =Staff!A5 -> Junior Researcher | C6: =Staff!E5 -> 32500 | D6: 0.8 | E6: =C6*D6 -> 26000 | F6: =1-D6 -> 0.2 | G6: =C6*F6 -> 6500
B7: =Staff!A6 -> Junior Researcher II | C7: =Staff!E6 -> 32500 | D7: 0.8 | E7: =C7*D7 -> 26000 | F7: =1-D7 -> 0.2 | G7: =C7*F7 -> 6500
B8: TOTAL | C8: =Staff!E7 -> 215800 | E8: =SUM(E3:E7) -> 123500 | G8: =SUM(G3:G7) -> 92300

Sheet Indirect Costs
B2: Service | C2: Monthly Cost | D2: Yearly Cost
B3: Cleaning | C3: 20 | D3: =C3*12 -> 240
B4: Light Consumption | C4: 70 | D4: =C4*12 -> 840
B5: Water Consumption | C5: 20 | D5: =C5*12 -> 240
B6: Heating | C6: 20 | D6: =C6*12 -> 240
B7: Internet provider | C7: 65.99 | D7: =C7*12 -> 791.88
B8: Movility Costs | C8: 40 | D8: =C8*12 -> 480
B9: Total | D9: =SUM(D3:D8) -> 2831.88

Sheet Production Costs
B2: License/Team | C2: Units | D2: Price | E2: Total Price | F2: Annual Cost | G2: Type | H2: Term
B3: Tobii pro nano | C3: 1 | D3: 2500 | E3: =C3*D3 -> 2500 | F3: =E3/12 -> 208.33333 | G3: Amortization | H3: -
B4: Tobii pro lab license | C4: 1 | D4: 1800 | E4: =C4*D4 -> 1800 | F4: =E4/12 -> 150 | G4: Amortization | H4: -
B5: Total | F5: =SUM(F3:F4) -> 358.33333

Sheet Billing Needs
B5: Indirect plus direct costs | C5: ='Production Costs'!F5+'Indirect Costs'!D9+'Staff Productivity'!C8 -> 218990.21
B6: Desired Benefit | C6: =C5*F6 -> 54747.553 | E6: Desired Benefit | F6: 0.25
B7: Billing Needs | C7: =C5+C6 -> 273737.77

Sheet Schedule
B2: Staff | C2: Prod(%) | D2: Hours / year | E2: Productive hours / year (per person) | F2: Productive Hours (Total)
B3: =Staff!A2 -> Project Manager | C3: ='Staff Productivity'!D3 -> 0 | D3: 1784 | E3: =D3*C3 -> 0 | F3: =E3 -> 0
B4: =Staff!A3 -> Lead Researcher | C4: ='Staff Productivity'!D4 -> 0.7 | D4: 1784 | E4: =D4*C4 -> 1248.8 | F4: =E4 -> 1248.8
B5: =Staff!A4 -> Software Engineer | C5: ='Staff Productivity'!D5 -> 0.8 | D5: 1784 | E5: =D5*C5 -> 1427.2 | F5: =E5 -> 1427.2
B6: =Staff!A5 -> Junior Researcher | C6: ='Staff Productivity'!D6 -> 0.8 | D6: 1784 | E6: =D6*C6 -> 1427.2 | F6: =E6 -> 1427.2
B7: =Staff!A6 -> Junior Researcher II | C7: ='Staff Productivity'!D7 -> 0.8 | D7: 1784 | E7: =D7*C7 -> 1427.2 | F7: =E7 -> 1427.2
B8: Total | F8: =SUM(F3:F7) -> 5530.4

Sheet Price per Hour
B2: Staff | C2: Price / hour | D2: Price /hour with no benefit | E2: Productive Hours | F2: Billing
B3: =Staff!A2 -> Project Manager | C3: =D3*(1+'Billing Needs'!$F$6) -> 0 | D3: 0 | E3: =Schedule!F3 -> 0 | F3: =C4*E3 -> 0
B4: =Staff!A3 -> Lead Researcher | C4: =D4*(1+'Billing Needs'!$F$6) -> 70 | D4: =ROUNDUP(((Staff!D3+$E$13)/E4),0) -> 56 | E4: =Schedule!F4 -> 1248.8 | F4: =C4*E4 -> 87416
B5: =Staff!A4 -> Software Engineer | C5: =D5*(1+'Billing Needs'!$F$6) -> 50 | D5: =ROUNDUP(((Staff!D4+$E$13)/E5),0) -> 40 | E5: =Schedule!F5 -> 1427.2 | F5: =C5*E5 -> 71360
B6: =Staff!A5 -> Junior Researcher | C6: =D6*(1+'Billing Needs'!$F$6) -> 41.25 | D6: =ROUNDUP(((Staff!D5+$E$13)/E6),0) -> 33 | E6: =Schedule!F6 -> 1427.2 | F6: =C6*E6 -> 58872
B7: =Staff!A6 -> Junior Researcher II | C7: =D7*(1+'Billing Needs'!$F$6) -> 41.25 | D7: =ROUNDUP(((Staff!D6+$E$13)/E7),0) -> 33 | E7: =Schedule!F7 -> 1427.2 | F7: =C7*E7 -> 58872
B8: Total | F8: =SUM(F4:F7) -> 276520
B11: Indirect | C11: Means | D11: Non productive
B12: ='Indirect Costs'!D9 -> 2831.88 | C12: ='Production Costs'!F5 -> 358.33333 | D12: ='Staff Productivity'!G3 -> 54600
A13: Notes to calc | B13: =B12/(Staff!$B$7-1) -> 707.97 | C13: =C12/(Staff!$B$7-1) -> 89.583333 | D13: =D12/(Staff!$B$7-1) -> 13650 | E13: =SUM(B13:D13) -> 14447.553

Sheet Summary
B2: Concept
B3: Total direct costs | C3: ='Staff Productivity'!E8 -> 123500
B4: Total Indirect Costs | C4: ='Staff Productivity'!G8+'Indirect Costs'!D9+'Production Costs'!F5 -> 95490.213
B5: Sum of both direct and indirect costs | C5: =C3+C4 -> 218990.21
B6: Desired Benefit | C6: ='Billing Needs'!C6 -> 54747.553
B7: Total Cost (Sum of costs + benefit) | C7: =C6+C5 -> 273737.77
B8: Possible billing by productivity hours and price per hour | C8: ='Price per Hour'!F8 -> 276520
B9: Total cost and billing costs margin | C9: =C8/C7-1 -> 0.010163864

Sheet Budget
B2: Code | C2: Number | D2: Part | E2: Total
B3: 1 | D3: Previous Planning and State of the art | E3: ='Part 1'!M39 -> 6622.5
C4: 1 | D4: Previous Planning | E4: ='Part 1'!M3 -> 1005
C5: 2 | D5: State of the Art | E5: ='Part 1'!M26 -> 5617.5
B6: 2 | D6: Experiment | E6: ='Part 2'!M39 -> 13588.75 | F6: =E6*(1+E$15) -> 23991.575
C7: 1 | D7: Experiment Proposal | E7: ='Part 2'!M3 -> 2943.75 | F7: =E7*(1+E$15) -> 5197.3285
C8: 2 | D8: Experiment Development | E8: ='Part 2'!M12 -> 2722.5 | F8: =E8*(1+E$15) -> 4806.7013
C9: 3 | D9: Data analysis | E9: ='Part 2'!M20 -> 7922.5 | F9: =E9*(1+E$15) -> 13987.545
B10: 3 | D10: Documentation for the paper | E10: ='Part 3'!K21 -> 3041.25 | F10: =E10*(1+E$15) -> 5369.4693
D11: Total | E11: =E3+E6+E10 -> 23252.5 | F11: =F6+F10 -> 29361.044
D12: Total con beneficios | E12: =E11*(1+'Billing Needs'!$F$6) -> 29065.625
D13: Contingencia | E13: =Summary!C9*E12 -> 295.41905
D14: Beneficio total | E14: =(E13+E12)-E11 -> 6108.544
D15: Porcentaje de Reparticion al Cliente | E15: =(E14+E3)/(E11-E3) -> 0.76554685

Sheet Client
B2: Code | C2: Number | D2: Part | E2: Total
B3: 1 | D3: Experiment | E3: =Budget!F6 -> 23991.575
C4: 1 | D4: Experiment Proposal | E4: =Budget!F7 -> 5197.3285
C5: 2 | D5: Experiment Development | E5: =Budget!F8 -> 4806.7013
C6: 3 | D6: Data analysis | E6: =Budget!F9 -> 13987.545
B7: 2 | D7: Documentation for the paper | E7: =Budget!F10 -> 5369.4693
B8: Total | E8: =E3+E7 -> 29361.044

Sheet Part 1
B2: Index 1 | C2: Index 2 | D2: Index 3 | E2: Index 4 | F2: Task Name | G2: Quantity | H2: Units | I2: Price | J2: Subtotal(3) | K2: Subtotal (2) | L2: Subtotal(1) | M2: Total
B3: 001 | F3: Previous Planning | M3: =L4+L9+L17 -> 1005
C4: 001 | F4: Research Process Planning | L4: =K5 -> 0
D5: 001 | F5: Needs Analysis | K5: =J6 -> 0
E6: 001 | F6: Project Manager | G6: 6 | H6: Hours | I6: ='Price per Hour'!C3 -> 0 | J6: =I6*G6 -> 0
D7: 002 | F7: Organization and definition of roles
E8: 001 | F8: Project Manager | G8: 3 | H8: Hours | I8: ='Price per Hour'!C3 -> 0 | J8: =I8*G8 -> 0
C9: 002 | F9: Definition of technology needs | L9: =K10+K12+K15 -> 1005
D10: 001 | F10: Identification of technology needs | K10: =J11 -> 210
E11: 001 | F11: Lead Researcher | G11: 3 | H11: Hours | I11: ='Price per Hour'!C4 -> 70 | J11: =I11*G11 -> 210
D12: 002 | F12: Selection of tools and technologies | K12: =SUM(J13:J14) -> 720
E13: 001 | F13: Lead Researcher | G13: 6 | H13: Hours | I13: ='Price per Hour'!C4 -> 70 | J13: =I13*G13 -> 420
E14: 002 | F14: Software Engineer | G14: 6 | H14: Hours | I14: ='Price per Hour'!C5 -> 50 | J14: =I14*G14 -> 300
D15: 003 | F15: Acquisition of chosen technologies | K15: =J16 -> 75
E16: 001 | F16: Software Engineer | G16: 1.5 | H16: Hours | I16: ='Price per Hour'!C5 -> 50 | J16: =I16*G16 -> 75
C17: 003 | F17: Project Planning | L17: =K18+K20+K22+K24 -> 0
D18: 001 | F18: OBS | K18: =J19 -> 0
E19: 001 | F19: Project Manager | G19: 3 | H19: Hours | I19: ='Price per Hour'!C3 -> 0 | J19: =I19*G19 -> 0
D20: 002 | F20: WBS | K20: =J21 -> 0
E21: 001 | F21: Project Manager | G21: 18 | H21: Hours | I21: ='Price per Hour'!C3 -> 0 | J21: =I21*G21 -> 0
D22: 003 | F22: Risk Management | K22: =J23 -> 0
E23: 001 | F23: Project Manager | G23: 18 | H23: Hours | I23: ='Price per Hour'!C3 -> 0 | J23: =I23*G23 -> 0
D24: 004 | F24: Budget Creation | K24: =J25 -> 0
E25: 001 | F25: Project Manager | G25: 18 | H25: Hours | I25: ='Price per Hour'!C3 -> 0 | J25: =I25*G25 -> 0
B26: 002 | F26: State of the art | M26: =L27+L30+L33+L36 -> 5617.5
C27: 001 | F27: Search and analysis | L27: =K28+K29 -> 2722.5
D28: 001 | F28: Junior Researcher 1 | G28: 33 | H28: Hours | I28: ='Price per Hour'!C6 -> 41.25 | K28: =G28*I28 -> 1361.25
D29: 002 | F29: Junior Researcher 2 | G29: 33 | H29: Hours | I29: ='Price per Hour'!C7 -> 41.25 | K29: =G29*I29 -> 1361.25
C30: 002 | F30: First Bake | L30: =K31+K32 -> 1237.5
D31: 001 | F31: Junior Researcher 1 | G31: 15 | H31: Hours | I31: ='Price per Hour'!C6 -> 41.25 | K31: =G31*I31 -> 618.75
D32: 002 | F32: Junior Researcher 2 | G32: 15 | H32: Hours | I32: ='Price per Hour'!C7 -> 41.25 | K32: =G32*I32 -> 618.75
C33: 003 | F33: Second and final bake | L33: =K34+K35 -> 1237.5
D34: 001 | F34: Junior Researcher 1 | G34: 15 | H34: Hours | I34: ='Price per Hour'!C6 -> 41.25 | K34: =G34*I34 -> 618.75
D35: 002 | F35: Junior Researcher 2 | G35: 15 | H35: Hours | I35: ='Price per Hour'!C7 -> 41.25 | K35: =G35*I35 -> 618.75
C36: 004 | F36: Final Presentation | L36: =K37 -> 420
D37: 001 | F37: Lead Researcher | G37: 6 | H37: Hours | I37: ='Price per Hour'!C4 -> 70 | K37: =G37*I37 -> 420
B39: TOTAL | M39: =SUM(M3:M37) -> 6622.5

Sheet Part 2
B2: Index 1 | C2: Index 2 | D2: Index 3 | E2: Index 4 | F2: Task Name | G2: Quantity | H2: Units | I2: Price | J2: Subtotal(3) | K2: Subtotal (2) | L2: Subtotal(1) | M2: Total
B3: 001 | F3: Experiment Proposal | M3: =L4+L6+L8+L10 -> 2943.75
C4: 001 | F4: In depth experiment creation | L4: =K5 -> 2100
D5: 001 | F5: Lead Researcher | G5: 30 | H5: Hours | I5: ='Price per Hour'!C$4 -> 70 | K5: =I5*G5 -> 2100
C6: 002 | F6: Webpage selection | L6: =K7 -> 300
D7: 001 | F7: Software Engineer | G7: 6 | H7: Hours | I7: ='Price per Hour'!C$5 -> 50 | K7: =I7*G7 -> 300
C8: 003 | F8: Creation of the form | L8: =K9 -> 123.75
D9: 001 | F9: Junior Researcher 2 | G9: 3 | H9: Hours | I9: ='Price per Hour'!C$7 -> 41.25 | K9: =I9*G9 -> 123.75
C10: 004 | F10: Tobii pro lab configuration | L10: =K11 -> 420
D11: 001 | F11: Lead Researcher | G11: 6 | H11: Hours | I11: ='Price per Hour'!C$4 -> 70 | K11: =I11*G11 -> 420
B12: 002 | F12: Experiment Development | M12: =L13+L16+L17 -> 2722.5
C13: 001 | F13: Book the desired place | L13: =K14 -> 247.5
D14: 001 | F14: Junior Researcher 1 | G14: 6 | H14: Hours | I14: ='Price per Hour'!C$6 -> 41.25 | K14: =I14*G14 -> 247.5
C15: 002 | F15: Preparation of material | L15: =K16 -> 247.5
D16: 001 | F16: Junior Researcher 2 | G16: 6 | H16: Hours | I16: ='Price per Hour'!C$7 -> 41.25 | K16: =I16*G16 -> 247.5
C17: 003 | F17: Data Retrieval | L17: =K18+K19 -> 2475
D18: 001 | F18: Junior Researcher 1 | G18: 30 | H18: Hours | I18: ='Price per Hour'!C$6 -> 41.25 | K18: =I18*G18 -> 1237.5
D19: 002 | F19: Junior Researcher 2 | G19: 30 | H19: Hours | I19: ='Price per Hour'!C$7 -> 41.25 | K19: =I19*G19 -> 1237.5
B20: 003 | F20: Data analysis | M20: =L21+L28+L30+L32+L34 -> 7922.5
C21: 001 | F21: Data preprocessing | L21: =K22+K24+K26 -> 2190
D22: 001 | F22: Tobii pro lab AOI creation | K22: =J23 -> 990
E23: 001 | F23: Junior Researcher 1 | G23: 24 | H23: Hours | I23: ='Price per Hour'!C$6 -> 41.25 | J23: =I23*G23 -> 990
D24: 002 | F24: Data Download | K24: =J25 -> 300
E25: 001 | F25: Software Engineer | G25: 6 | H25: Hours | I25: ='Price per Hour'!C$5 -> 50 | J25: =I25*G25 -> 300
D26: 003 | F26: Preprocessing implementation | K26: =J27 -> 900
E27: 001 | F27: Software Engineer | G27: 18 | H27: Hours | I27: ='Price per Hour'!C$5 -> 50 | J27: =I27*G27 -> 900
C28: 002 | F28: Data processing | L28: =K29 -> 1800
D29: 001 | F29: Software Engineer | G29: 36 | H29: Hours | I29: ='Price per Hour'!C$5 -> 50 | K29: =G29*I29 -> 1800
C30: 003 | F30: Statistical Study | L30: =K31 -> 1680
D31: 001 | F31: Lead Researcher | G31: 24 | H31: Hours | I31: ='Price per Hour'!C$4 -> 70 | K31: =G31*I31 -> 1680
C32: 004 | F32: Collect conclussions and results | L32: =K33 -> 2100
D33: 001 | F33: Lead Researcher | G33: 30 | H33: Hours | I33: ='Price per Hour'!C$4 -> 70 | K33: =G33*I33 -> 2100
C34: 005 | F34: Final meeting | L34: =K35+K36+K37 -> 152.5
D35: 001 | F35: Junior Researcher 1 | G35: 1 | H35: Hours | I35: ='Price per Hour'!C$6 -> 41.25 | K35: =G35*I35 -> 41.25
D36: 002 | F36: Junior Researcher 2 | G36: 1 | H36: Hours | I36: ='Price per Hour'!C$7 -> 41.25 | K36: =G36*I36 -> 41.25
D37: 003 | F37: Lead Researcher | G37: 1 | H37: Hours | I37: ='Price per Hour'!C$4 -> 70 | K37: =G37*I37 -> 70
B39: TOTAL | M39: =SUM(M3:M37) -> 13588.75

Sheet Part 3
B2: Index 1 | C2: Index 2 | D2: Index 3 | E2: Task Name | F2: Quantity | G2: Units | H2: Price | I2: Subtotal (2) | J2: Subtotal(1) | K2: Total
B3: 001 | E3: Documentation | K3: =J4+J6+J8+J10+J12+J14+J16+J18 -> 3041.25
C4: 001 | E4: Abstract Writing | J4: =I5 -> 123.75
D5: 001 | E5: Junior Researcher 1 | F5: 3 | G5: Hours | H5: ='Price per Hour'!C$6 -> 41.25 | I5: =H5*F5 -> 123.75
C6: 002 | E6: Introduction Writing | J6: =I7 -> 123.75
D7: 001 | E7: Junior Researcher 2 | F7: 3 | G7: Hours | H7: ='Price per Hour'!C$7 -> 41.25 | I7: =H7*F7 -> 123.75
C8: 003 | E8: Literature Writing | J8: =I9 -> 123.75
D9: 001 | E9: Junior Researcher 1 | F9: 3 | G9: Hours | H9: ='Price per Hour'!C$6 -> 41.25 | I9: =H9*F9 -> 123.75
C10: 004 | E10: Method Writing | J10: =I11 -> 247.5
D11: 001 | E11: Junior Researcher 2 | F11: 6 | G11: Hours | H11: ='Price per Hour'!C$7 -> 41.25 | I11: =H11*F11 -> 247.5
C12: 005 | E12: Results and discussion writing | J12: =I13 -> 495
D13: 001 | E13: Junior Researcher 1 | F13: 12 | G13: Hours | H13: ='Price per Hour'!C$6 -> 41.25 | I13: =H13*F13 -> 495
C14: 006 | E14: Conclusion Writing | J14: =I15 -> 247.5
D15: 001 | E15: Junior Researcher 2 | F15: 6 | G15: Hours | H15: ='Price per Hour'!C$7 -> 41.25 | I15: =H15*F15 -> 247.5
C16: 007 | E16: Reference review | J16: =I17 -> 420
D17: 001 | E17: Lead Researcher | F17: 6 | G17: Hours | H17: ='Price per Hour'!C$4 -> 70 | I17: =H17*F17 -> 420
C18: 008 | E18: Final documentation review | J18: =I19 -> 1260
D19: 002 | E19: Lead Researcher | F19: 18 | G19: Hours | H19: ='Price per Hour'!C$4 -> 70 | I19: =H19*F19 -> 1260
B21: TOTAL | K21: =SUM(K3:K19) -> 3041.25
